{"nodes": [{"id": "users_chenxi_kits_keikeu_src_keikeu_app_py", "label": "app.py", "file_type": "code", "source_file": "/Users/chenxi/kits/keikeu/src/keikeu/app.py", "source_location": "L1"}, {"id": "keikeu_app_keikeuapp", "label": "KeikeuApp", "file_type": "code", "source_file": "/Users/chenxi/kits/keikeu/src/keikeu/app.py", "source_location": "L14"}, {"id": "keikeu_app_keikeuapp_init", "label": ".__init__()", "file_type": "code", "source_file": "/Users/chenxi/kits/keikeu/src/keikeu/app.py", "source_location": "L15"}, {"id": "keikeu_app_keikeuapp_set_output", "label": "._set_output()", "file_type": "code", "source_file": "/Users/chenxi/kits/keikeu/src/keikeu/app.py", "source_location": "L83"}, {"id": "str", "label": "str", "file_type": "code", "source_file": "/Users/chenxi/kits/keikeu/src/keikeu/app.py", "source_location": "L83"}, {"id": "keikeu_app_keikeuapp_on_generate", "label": "._on_generate()", "file_type": "code", "source_file": "/Users/chenxi/kits/keikeu/src/keikeu/app.py", "source_location": "L90"}, {"id": "keikeu_app_keikeuapp_on_clear", "label": "._on_clear()", "file_type": "code", "source_file": "/Users/chenxi/kits/keikeu/src/keikeu/app.py", "source_location": "L103"}, {"id": "keikeu_app_keikeuapp_on_copy", "label": "._on_copy()", "file_type": "code", "source_file": "/Users/chenxi/kits/keikeu/src/keikeu/app.py", "source_location": "L109"}, {"id": "keikeu_app_main", "label": "main()", "file_type": "code", "source_file": "/Users/chenxi/kits/keikeu/src/keikeu/app.py", "source_location": "L125"}], "edges": [{"source": "users_chenxi_kits_keikeu_src_keikeu_app_py", "target": "customtkinter", "relation": "imports", "context": "import", "confidence": "EXTRACTED", "source_file": "/Users/chenxi/kits/keikeu/src/keikeu/app.py", "source_location": "L3", "weight": 1.0}, {"source": "users_chenxi_kits_keikeu_src_keikeu_app_py", "target": "users_chenxi_kits_keikeu_src_keikeu_clipboard_py", "relation": "imports_from", "context": "import", "confidence": "EXTRACTED", "source_file": "/Users/chenxi/kits/keikeu/src/keikeu/app.py", "source_location": "L5", "weight": 1.0}, {"source": "users_chenxi_kits_keikeu_src_keikeu_app_py", "target": "users_chenxi_kits_keikeu_src_keikeu_generator_py", "relation": "imports_from", "context": "import", "confidence": "EXTRACTED", "source_file": "/Users/chenxi/kits/keikeu/src/keikeu/app.py", "source_location": "L6", "weight": 1.0}, {"source": "users_chenxi_kits_keikeu_src_keikeu_app_py", "target": "users_chenxi_kits_keikeu_src_keikeu_renderers_py", "relation": "imports_from", "context": "import", "confidence": "EXTRACTED", "source_file": "/Users/chenxi/kits/keikeu/src/keikeu/app.py", "source_location": "L7", "weight": 1.0}, {"source": "users_chenxi_kits_keikeu_src_keikeu_app_py", "target": "keikeu_app_keikeuapp", "relation": "contains", "confidence": "EXTRACTED", "source_file": "/Users/chenxi/kits/keikeu/src/keikeu/app.py", "source_location": "L14", "weight": 1.0}, {"source": "keikeu_app_keikeuapp", "target": "keikeu_app_keikeuapp_init", "relation": "method", "confidence": "EXTRACTED", "source_file": "/Users/chenxi/kits/keikeu/src/keikeu/app.py", "source_location": "L15", "weight": 1.0}, {"source": "keikeu_app_keikeuapp", "target": "keikeu_app_keikeuapp_set_output", "relation": "method", "confidence": "EXTRACTED", "source_file": "/Users/chenxi/kits/keikeu/src/keikeu/app.py", "source_location": "L83", "weight": 1.0}, {"source": "keikeu_app_keikeuapp_set_output", "target": "str", "relation": "references", "context": "parameter_type", "confidence": "EXTRACTED", "source_file": "/Users/chenxi/kits/keikeu/src/keikeu/app.py", "source_location": "L83", "weight": 1.0}, {"source": "keikeu_app_keikeuapp_set_output", "target": "str", "relation": "references", "context": "parameter_type", "confidence": "EXTRACTED", "source_file": "/Users/chenxi/kits/keikeu/src/keikeu/app.py", "source_location": "L83", "weight": 1.0}, {"source": "keikeu_app_keikeuapp", "target": "keikeu_app_keikeuapp_on_generate", "relation": "method", "confidence": "EXTRACTED", "source_file": "/Users/chenxi/kits/keikeu/src/keikeu/app.py", "source_location": "L90", "weight": 1.0}, {"source": "keikeu_app_keikeuapp", "target": "keikeu_app_keikeuapp_on_clear", "relation": "method", "confidence": "EXTRACTED", "source_file": "/Users/chenxi/kits/keikeu/src/keikeu/app.py", "source_location": "L103", "weight": 1.0}, {"source": "keikeu_app_keikeuapp", "target": "keikeu_app_keikeuapp_on_copy", "relation": "method", "confidence": "EXTRACTED", "source_file": "/Users/chenxi/kits/keikeu/src/keikeu/app.py", "source_location": "L109", "weight": 1.0}, {"source": "users_chenxi_kits_keikeu_src_keikeu_app_py", "target": "keikeu_app_main", "relation": "contains", "confidence": "EXTRACTED", "source_file": "/Users/chenxi/kits/keikeu/src/keikeu/app.py", "source_location": "L125", "weight": 1.0}, {"source": "keikeu_app_keikeuapp_on_generate", "target": "keikeu_app_keikeuapp_set_output", "relation": "calls", "context": "call", "confidence": "EXTRACTED", "source_file": "/Users/chenxi/kits/keikeu/src/keikeu/app.py", "source_location": "L99", "weight": 1.0}, {"source": "keikeu_app_keikeuapp_on_clear", "target": "keikeu_app_keikeuapp_set_output", "relation": "calls", "context": "call", "confidence": "EXTRACTED", "source_file": "/Users/chenxi/kits/keikeu/src/keikeu/app.py", "source_location": "L106", "weight": 1.0}, {"source": "keikeu_app_main", "target": "keikeu_app_keikeuapp", "relation": "calls", "context": "call", "confidence": "EXTRACTED", "source_file": "/Users/chenxi/kits/keikeu/src/keikeu/app.py", "source_location": "L126", "weight": 1.0}], "raw_calls": [{"caller_nid": "keikeu_app_keikeuapp_init", "callee": "title", "is_member_call": true, "source_file": "/Users/chenxi/kits/keikeu/src/keikeu/app.py", "source_location": "L17"}, {"caller_nid": "keikeu_app_keikeuapp_init", "callee": "geometry", "is_member_call": true, "source_file": "/Users/chenxi/kits/keikeu/src/keikeu/app.py", "source_location": "L18"}, {"caller_nid": "keikeu_app_keikeuapp_init", "callee": "minsize", "is_member_call": true, "source_file": "/Users/chenxi/kits/keikeu/src/keikeu/app.py", "source_location": "L19"}, {"caller_nid": "keikeu_app_keikeuapp_init", "callee": "set_appearance_mode", "is_member_call": true, "source_file": "/Users/chenxi/kits/keikeu/src/keikeu/app.py", "source_location": "L21"}, {"caller_nid": "keikeu_app_keikeuapp_init", "callee": "set_default_color_theme", "is_member_call": true, "source_file": "/Users/chenxi/kits/keikeu/src/keikeu/app.py", "source_location": "L22"}, {"caller_nid": "keikeu_app_keikeuapp_init", "callee": "grid_columnconfigure", "is_member_call": true, "source_file": "/Users/chenxi/kits/keikeu/src/keikeu/app.py", "source_location": "L24"}, {"caller_nid": "keikeu_app_keikeuapp_init", "callee": "grid_rowconfigure", "is_member_call": true, "source_file": "/Users/chenxi/kits/keikeu/src/keikeu/app.py", "source_location": "L25"}, {"caller_nid": "keikeu_app_keikeuapp_init", "callee": "grid", "is_member_call": true, "source_file": "/Users/chenxi/kits/keikeu/src/keikeu/app.py", "source_location": "L27"}, {"caller_nid": "keikeu_app_keikeuapp_init", "callee": "CTkLabel", "is_member_call": true, "source_file": "/Users/chenxi/kits/keikeu/src/keikeu/app.py", "source_location": "L27"}, {"caller_nid": "keikeu_app_keikeuapp_init", "callee": "CTkFont", "is_member_call": true, "source_file": "/Users/chenxi/kits/keikeu/src/keikeu/app.py", "source_location": "L30"}, {"caller_nid": "keikeu_app_keikeuapp_init", "callee": "CTkTextbox", "is_member_call": true, "source_file": "/Users/chenxi/kits/keikeu/src/keikeu/app.py", "source_location": "L34"}, {"caller_nid": "keikeu_app_keikeuapp_init", "callee": "grid", "is_member_call": true, "source_file": "/Users/chenxi/kits/keikeu/src/keikeu/app.py", "source_location": "L35"}, {"caller_nid": "keikeu_app_keikeuapp_init", "callee": "insert", "is_member_call": true, "source_file": "/Users/chenxi/kits/keikeu/src/keikeu/app.py", "source_location": "L36"}, {"caller_nid": "keikeu_app_keikeuapp_init", "callee": "CTkFrame", "is_member_call": true, "source_file": "/Users/chenxi/kits/keikeu/src/keikeu/app.py", "source_location": "L41"}, {"caller_nid": "keikeu_app_keikeuapp_init", "callee": "grid", "is_member_call": true, "source_file": "/Users/chenxi/kits/keikeu/src/keikeu/app.py", "source_location": "L42"}, {"caller_nid": "keikeu_app_keikeuapp_init", "callee": "grid_columnconfigure", "is_member_call": true, "source_file": "/Users/chenxi/kits/keikeu/src/keikeu/app.py", "source_location": "L43"}, {"caller_nid": "keikeu_app_keikeuapp_init", "callee": "grid", "is_member_call": true, "source_file": "/Users/chenxi/kits/keikeu/src/keikeu/app.py", "source_location": "L45"}, {"caller_nid": "keikeu_app_keikeuapp_init", "callee": "CTkButton", "is_member_call": true, "source_file": "/Users/chenxi/kits/keikeu/src/keikeu/app.py", "source_location": "L45"}, {"caller_nid": "keikeu_app_keikeuapp_init", "callee": "grid", "is_member_call": true, "source_file": "/Users/chenxi/kits/keikeu/src/keikeu/app.py", "source_location": "L48"}, {"caller_nid": "keikeu_app_keikeuapp_init", "callee": "CTkButton", "is_member_call": true, "source_file": "/Users/chenxi/kits/keikeu/src/keikeu/app.py", "source_location": "L48"}, {"caller_nid": "keikeu_app_keikeuapp_init", "callee": "CTkLabel", "is_member_call": true, "source_file": "/Users/chenxi/kits/keikeu/src/keikeu/app.py", "source_location": "L57"}, {"caller_nid": "keikeu_app_keikeuapp_init", "callee": "grid", "is_member_call": true, "source_file": "/Users/chenxi/kits/keikeu/src/keikeu/app.py", "source_location": "L60"}, {"caller_nid": "keikeu_app_keikeuapp_init", "callee": "CTkTabview", "is_member_call": true, "source_file": "/Users/chenxi/kits/keikeu/src/keikeu/app.py", "source_location": "L62"}, {"caller_nid": "keikeu_app_keikeuapp_init", "callee": "grid", "is_member_call": true, "source_file": "/Users/chenxi/kits/keikeu/src/keikeu/app.py", "source_location": "L63"}, {"caller_nid": "keikeu_app_keikeuapp_init", "callee": "grid_rowconfigure", "is_member_call": true, "source_file": "/Users/chenxi/kits/keikeu/src/keikeu/app.py", "source_location": "L64"}, {"caller_nid": "keikeu_app_keikeuapp_init", "callee": "add", "is_member_call": true, "source_file": "/Users/chenxi/kits/keikeu/src/keikeu/app.py", "source_location": "L68"}, {"caller_nid": "keikeu_app_keikeuapp_init", "callee": "grid_columnconfigure", "is_member_call": true, "source_file": "/Users/chenxi/kits/keikeu/src/keikeu/app.py", "source_location": "L69"}, {"caller_nid": "keikeu_app_keikeuapp_init", "callee": "grid_rowconfigure", "is_member_call": true, "source_file": "/Users/chenxi/kits/keikeu/src/keikeu/app.py", "source_location": "L70"}, {"caller_nid": "keikeu_app_keikeuapp_init", "callee": "CTkTextbox", "is_member_call": true, "source_file": "/Users/chenxi/kits/keikeu/src/keikeu/app.py", "source_location": "L71"}, {"caller_nid": "keikeu_app_keikeuapp_init", "callee": "grid", "is_member_call": true, "source_file": "/Users/chenxi/kits/keikeu/src/keikeu/app.py", "source_location": "L72"}, {"caller_nid": "keikeu_app_keikeuapp_init", "callee": "configure", "is_member_call": true, "source_file": "/Users/chenxi/kits/keikeu/src/keikeu/app.py", "source_location": "L73"}, {"caller_nid": "keikeu_app_keikeuapp_init", "callee": "grid", "is_member_call": true, "source_file": "/Users/chenxi/kits/keikeu/src/keikeu/app.py", "source_location": "L76"}, {"caller_nid": "keikeu_app_keikeuapp_init", "callee": "CTkButton", "is_member_call": true, "source_file": "/Users/chenxi/kits/keikeu/src/keikeu/app.py", "source_location": "L76"}, {"caller_nid": "keikeu_app_keikeuapp_set_output", "callee": "configure", "is_member_call": true, "source_file": "/Users/chenxi/kits/keikeu/src/keikeu/app.py", "source_location": "L85"}, {"caller_nid": "keikeu_app_keikeuapp_set_output", "callee": "delete", "is_member_call": true, "source_file": "/Users/chenxi/kits/keikeu/src/keikeu/app.py", "source_location": "L86"}, {"caller_nid": "keikeu_app_keikeuapp_set_output", "callee": "insert", "is_member_call": true, "source_file": "/Users/chenxi/kits/keikeu/src/keikeu/app.py", "source_location": "L87"}, {"caller_nid": "keikeu_app_keikeuapp_set_output", "callee": "configure", "is_member_call": true, "source_file": "/Users/chenxi/kits/keikeu/src/keikeu/app.py", "source_location": "L88"}, {"caller_nid": "keikeu_app_keikeuapp_on_generate", "callee": "get", "is_member_call": true, "source_file": "/Users/chenxi/kits/keikeu/src/keikeu/app.py", "source_location": "L91"}, {"caller_nid": "keikeu_app_keikeuapp_on_generate", "callee": "make_ticket", "is_member_call": false, "source_file": "/Users/chenxi/kits/keikeu/src/keikeu/app.py", "source_location": "L93"}, {"caller_nid": "keikeu_app_keikeuapp_on_generate", "callee": "configure", "is_member_call": true, "source_file": "/Users/chenxi/kits/keikeu/src/keikeu/app.py", "source_location": "L95"}, {"caller_nid": "keikeu_app_keikeuapp_on_generate", "callee": "configure", "is_member_call": true, "source_file": "/Users/chenxi/kits/keikeu/src/keikeu/app.py", "source_location": "L98"}, {"caller_nid": "keikeu_app_keikeuapp_on_generate", "callee": "render_sop", "is_member_call": false, "source_file": "/Users/chenxi/kits/keikeu/src/keikeu/app.py", "source_location": "L99"}, {"caller_nid": "keikeu_app_keikeuapp_on_generate", "callee": "render_brief", "is_member_call": false, "source_file": "/Users/chenxi/kits/keikeu/src/keikeu/app.py", "source_location": "L100"}, {"caller_nid": "keikeu_app_keikeuapp_on_generate", "callee": "render_card", "is_member_call": false, "source_file": "/Users/chenxi/kits/keikeu/src/keikeu/app.py", "source_location": "L101"}, {"caller_nid": "keikeu_app_keikeuapp_on_clear", "callee": "delete", "is_member_call": true, "source_file": "/Users/chenxi/kits/keikeu/src/keikeu/app.py", "source_location": "L104"}, {"caller_nid": "keikeu_app_keikeuapp_on_clear", "callee": "configure", "is_member_call": true, "source_file": "/Users/chenxi/kits/keikeu/src/keikeu/app.py", "source_location": "L107"}, {"caller_nid": "keikeu_app_keikeuapp_on_copy", "callee": "get", "is_member_call": true, "source_file": "/Users/chenxi/kits/keikeu/src/keikeu/app.py", "source_location": "L110"}, {"caller_nid": "keikeu_app_keikeuapp_on_copy", "callee": "get", "is_member_call": true, "source_file": "/Users/chenxi/kits/keikeu/src/keikeu/app.py", "source_location": "L111"}, {"caller_nid": "keikeu_app_keikeuapp_on_copy", "callee": "rstrip", "is_member_call": true, "source_file": "/Users/chenxi/kits/keikeu/src/keikeu/app.py", "source_location": "L114"}, {"caller_nid": "keikeu_app_keikeuapp_on_copy", "callee": "get", "is_member_call": true, "source_file": "/Users/chenxi/kits/keikeu/src/keikeu/app.py", "source_location": "L114"}, {"caller_nid": "keikeu_app_keikeuapp_on_copy", "callee": "configure", "is_member_call": true, "source_file": "/Users/chenxi/kits/keikeu/src/keikeu/app.py", "source_location": "L116"}, {"caller_nid": "keikeu_app_keikeuapp_on_copy", "callee": "copy_to_clipboard", "is_member_call": false, "source_file": "/Users/chenxi/kits/keikeu/src/keikeu/app.py", "source_location": "L118"}, {"caller_nid": "keikeu_app_keikeuapp_on_copy", "callee": "configure", "is_member_call": true, "source_file": "/Users/chenxi/kits/keikeu/src/keikeu/app.py", "source_location": "L119"}, {"caller_nid": "keikeu_app_keikeuapp_on_copy", "callee": "after", "is_member_call": true, "source_file": "/Users/chenxi/kits/keikeu/src/keikeu/app.py", "source_location": "L122"}, {"caller_nid": "keikeu_app_keikeuapp_on_copy", "callee": "configure", "is_member_call": true, "source_file": "/Users/chenxi/kits/keikeu/src/keikeu/app.py", "source_location": "L122"}, {"caller_nid": "keikeu_app_main", "callee": "mainloop", "is_member_call": true, "source_file": "/Users/chenxi/kits/keikeu/src/keikeu/app.py", "source_location": "L127"}]}